voice_toolbox/__init__.py
voice_toolbox/feature_extraction.py
voice_toolbox/parsel_process.py
voice_toolbox-1.0.0.dist-info/METADATA
voice_toolbox-1.0.0.dist-info/WHEEL
voice_toolbox-1.0.0.dist-info/entry_points.txt
voice_toolbox-1.0.0.dist-info/top_level.txt
voice_toolbox-1.0.0.dist-info/RECORD
