Metadata-Version: 2.1
Name: voice_toolbox
Version: 1.0.0
Summary: Convenient wrappers for audio signal processing in Python
Author: Emma Hughson
Author-email: Paige Tuttosi <ptuttosi@gmail.com>
Keywords: audio,audio analysis
Classifier: Programming Language :: Python
Classifier: Programming Language :: Python :: 3
Classifier: Natural Language :: English
Classifier: Topic :: Multimedia :: Sound/Audio :: Analysis
Requires-Python: >=3.5
Requires-Dist: pandas >=1.4.1
Requires-Dist: numpy >=1.23.5
Requires-Dist: librosa >=0.9.0
Requires-Dist: scipy >=1.8.0
Requires-Dist: praat-parselmouth >=0.4.1
Requires-Dist: matplotlib >=3.5.1
Requires-Dist: SpeechRecognition >=3.8.1
Requires-Dist: syllables >=1.0.3
Requires-Dist: pydub >=0.25.1
